nrt_string_utils/__init__.py
nrt_string_utils/string_utils.py
nrt_string_utils-1.0.4.data/data/requirements.txt
nrt_string_utils-1.0.4.dist-info/licenses/LICENSE
nrt_string_utils-1.0.4.dist-info/METADATA
nrt_string_utils-1.0.4.dist-info/WHEEL
nrt_string_utils-1.0.4.dist-info/top_level.txt
nrt_string_utils-1.0.4.dist-info/RECORD
