Metadata-Version: 2.4
Name: nrt-string-utils
Version: 1.0.4
Summary: String utilities in Python
Home-page: https://github.com/etuzon/python-nrt-string-utils
Author: Eyal Tuzon
Author-email: Eyal Tuzon <eyal.tuzon.dev@gmail.com>
License-Expression: MIT
Project-URL: Homepage, https://github.com/etuzon/python-nrt-string-utils
Project-URL: Bug Tracker, https://github.com/etuzon/python-nrt-string-utils/issues
Project-URL: documentation, https://github.com/etuzon/python-nrt-string-utils/wiki
Keywords: python,python3,python-3,utilities,utils,util,tool,tools,nrt,nrt-utils,string,string-utils,string-utilities,nrt-string-utils,nrt-string-utilities
Classifier: Programming Language :: Python :: 3
Classifier: Programming Language :: Python :: 3.8
Classifier: Programming Language :: Python :: 3.9
Classifier: Programming Language :: Python :: 3.10
Classifier: Programming Language :: Python :: 3.11
Classifier: Programming Language :: Python :: 3.12
Classifier: Programming Language :: Python :: 3.13
Classifier: Programming Language :: Python :: 3.14
Classifier: Operating System :: OS Independent
Requires-Python: >=3.8
License-File: LICENSE
Dynamic: author
Dynamic: home-page
Dynamic: license-file
